{
  "id": "eec9c887-979f-49ab-afd9-25e18629e8eb",
  "prevId": "b9a15e87-775c-42eb-9761-2d19a6fe363e",
  "version": "7",
  "dialect": "postgresql",
  "tables": {
    "public.alert_rules": {
      "name": "alert_rules",
      "schema": "",
      "columns": {
        "id": {
          "name": "id",
          "type": "uuid",
          "primaryKey": true,
          "notNull": true,
          "default": "gen_random_uuid()"
        },
        "org_id": {
          "name": "org_id",
          "type": "uuid",
          "primaryKey": false,
          "notNull": true
        },
        "name": {
          "name": "name",
          "type": "text",
          "primaryKey": false,
          "notNull": true
        },
        "scope": {
          "name": "scope",
          "type": "text",
          "primaryKey": false,
          "notNull": true
        },
        "metric": {
          "name": "metric",
          "type": "text",
          "primaryKey": false,
          "notNull": true
        },
        "threshold": {
          "name": "threshold",
          "type": "numeric",
          "primaryKey": false,
          "notNull": true
        },
        "action": {
          "name": "action",
          "type": "text",
          "primaryKey": false,
          "notNull": true
        },
        "enabled": {
          "name": "enabled",
          "type": "boolean",
          "primaryKey": false,
          "notNull": true,
          "default": true
        },
        "created_at": {
          "name": "created_at",
          "type": "timestamp with time zone",
          "primaryKey": false,
          "notNull": true,
          "default": "now()"
        }
      },
      "indexes": {
        "alert_rules_org": {
          "name": "alert_rules_org",
          "columns": [
            {
              "expression": "org_id",
              "isExpression": false,
              "asc": true,
              "nulls": "last"
            }
          ],
          "isUnique": false,
          "concurrently": false,
          "method": "btree",
          "with": {}
        }
      },
      "foreignKeys": {
        "alert_rules_org_id_organizations_id_fk": {
          "name": "alert_rules_org_id_organizations_id_fk",
          "tableFrom": "alert_rules",
          "tableTo": "organizations",
          "columnsFrom": [
            "org_id"
          ],
          "columnsTo": [
            "id"
          ],
          "onDelete": "no action",
          "onUpdate": "no action"
        }
      },
      "compositePrimaryKeys": {},
      "uniqueConstraints": {},
      "policies": {},
      "checkConstraints": {},
      "isRLSEnabled": false
    },
    "public.notifications": {
      "name": "notifications",
      "schema": "",
      "columns": {
        "id": {
          "name": "id",
          "type": "uuid",
          "primaryKey": true,
          "notNull": true,
          "default": "gen_random_uuid()"
        },
        "org_id": {
          "name": "org_id",
          "type": "uuid",
          "primaryKey": false,
          "notNull": true
        },
        "type": {
          "name": "type",
          "type": "text",
          "primaryKey": false,
          "notNull": true
        },
        "severity": {
          "name": "severity",
          "type": "text",
          "primaryKey": false,
          "notNull": true
        },
        "title": {
          "name": "title",
          "type": "text",
          "primaryKey": false,
          "notNull": true
        },
        "body": {
          "name": "body",
          "type": "text",
          "primaryKey": false,
          "notNull": true,
          "default": "''"
        },
        "data": {
          "name": "data",
          "type": "jsonb",
          "primaryKey": false,
          "notNull": true,
          "default": "'{}'::jsonb"
        },
        "status": {
          "name": "status",
          "type": "text",
          "primaryKey": false,
          "notNull": true,
          "default": "'unread'"
        },
        "created_at": {
          "name": "created_at",
          "type": "timestamp with time zone",
          "primaryKey": false,
          "notNull": true,
          "default": "now()"
        },
        "read_at": {
          "name": "read_at",
          "type": "timestamp with time zone",
          "primaryKey": false,
          "notNull": false
        },
        "acked_at": {
          "name": "acked_at",
          "type": "timestamp with time zone",
          "primaryKey": false,
          "notNull": false
        }
      },
      "indexes": {
        "notifications_org_status": {
          "name": "notifications_org_status",
          "columns": [
            {
              "expression": "org_id",
              "isExpression": false,
              "asc": true,
              "nulls": "last"
            },
            {
              "expression": "status",
              "isExpression": false,
              "asc": true,
              "nulls": "last"
            }
          ],
          "isUnique": false,
          "concurrently": false,
          "method": "btree",
          "with": {}
        }
      },
      "foreignKeys": {
        "notifications_org_id_organizations_id_fk": {
          "name": "notifications_org_id_organizations_id_fk",
          "tableFrom": "notifications",
          "tableTo": "organizations",
          "columnsFrom": [
            "org_id"
          ],
          "columnsTo": [
            "id"
          ],
          "onDelete": "no action",
          "onUpdate": "no action"
        }
      },
      "compositePrimaryKeys": {},
      "uniqueConstraints": {},
      "policies": {},
      "checkConstraints": {},
      "isRLSEnabled": false
    },
    "public.organizations": {
      "name": "organizations",
      "schema": "",
      "columns": {
        "id": {
          "name": "id",
          "type": "uuid",
          "primaryKey": true,
          "notNull": true,
          "default": "gen_random_uuid()"
        },
        "slug": {
          "name": "slug",
          "type": "text",
          "primaryKey": false,
          "notNull": true
        },
        "name": {
          "name": "name",
          "type": "text",
          "primaryKey": false,
          "notNull": true
        },
        "default_currency": {
          "name": "default_currency",
          "type": "text",
          "primaryKey": false,
          "notNull": true,
          "default": "'USD'"
        },
        "created_at": {
          "name": "created_at",
          "type": "timestamp with time zone",
          "primaryKey": false,
          "notNull": true,
          "default": "now()"
        }
      },
      "indexes": {},
      "foreignKeys": {},
      "compositePrimaryKeys": {},
      "uniqueConstraints": {
        "organizations_slug_unique": {
          "name": "organizations_slug_unique",
          "nullsNotDistinct": false,
          "columns": [
            "slug"
          ]
        }
      },
      "policies": {},
      "checkConstraints": {},
      "isRLSEnabled": false
    },
    "public.products": {
      "name": "products",
      "schema": "",
      "columns": {
        "id": {
          "name": "id",
          "type": "uuid",
          "primaryKey": true,
          "notNull": true,
          "default": "gen_random_uuid()"
        },
        "org_id": {
          "name": "org_id",
          "type": "uuid",
          "primaryKey": false,
          "notNull": true
        },
        "key": {
          "name": "key",
          "type": "text",
          "primaryKey": false,
          "notNull": true
        },
        "name": {
          "name": "name",
          "type": "text",
          "primaryKey": false,
          "notNull": true
        },
        "created_at": {
          "name": "created_at",
          "type": "timestamp with time zone",
          "primaryKey": false,
          "notNull": true,
          "default": "now()"
        }
      },
      "indexes": {},
      "foreignKeys": {
        "products_org_id_organizations_id_fk": {
          "name": "products_org_id_organizations_id_fk",
          "tableFrom": "products",
          "tableTo": "organizations",
          "columnsFrom": [
            "org_id"
          ],
          "columnsTo": [
            "id"
          ],
          "onDelete": "no action",
          "onUpdate": "no action"
        }
      },
      "compositePrimaryKeys": {},
      "uniqueConstraints": {
        "products_org_key": {
          "name": "products_org_key",
          "nullsNotDistinct": false,
          "columns": [
            "org_id",
            "key"
          ]
        }
      },
      "policies": {},
      "checkConstraints": {},
      "isRLSEnabled": false
    }
  },
  "enums": {},
  "schemas": {},
  "sequences": {},
  "roles": {},
  "policies": {},
  "views": {},
  "_meta": {
    "columns": {},
    "schemas": {},
    "tables": {}
  }
}